extratorlattes/__init__.py
extratorlattes/carga.py
extratorlattes/carrega_Indicadores.py
extratorlattes/database.py
extratorlattes/faz_pareamento.py
extratorlattes/indicadores.py
extratorlattes/lattes.py
extratorlattes/pareamentos.py
extratorlattes/recebe_lattes.py
extratorlattes/regressao.py
extratorlattes-0.1.7.dist-info/licenses/COPYING
extratorlattes-0.1.7.dist-info/licenses/LICENCE
extratorlattes-0.1.7.dist-info/METADATA
extratorlattes-0.1.7.dist-info/WHEEL
extratorlattes-0.1.7.dist-info/top_level.txt
extratorlattes-0.1.7.dist-info/RECORD
