Metadata-Version: 2.4
Name: extratorlattes
Version: 0.1.7
Summary: Ferramenta para extração e pareamento de dados da Plataforma Lattes
Author: Alberto de Campos e Silva
Requires-Python: >=3.8
License-File: LICENCE
License-File: COPYING
Requires-Dist: pandas
Requires-Dist: numpy
Requires-Dist: xlsxwriter
Requires-Dist: psycopg2-binary
Requires-Dist: SQLAlchemy
Requires-Dist: statsmodels
Requires-Dist: Flask
Requires-Dist: requests
Requires-Dist: zeep
Requires-Dist: unidecode
Requires-Dist: xmltodict
Requires-Dist: beautifulsoup4
Requires-Dist: pytz
Dynamic: license-file
